<?xml version="1.0" encoding="UTF-8"?>
<configuration>

    <!-- Register Spring Boot's color and exception converters (%clr, %wEx) -->
    <conversionRule conversionWord="clr"
                    converterClass="org.springframework.boot.logging.logback.ColorConverter"/>
    <conversionRule conversionWord="wEx"
                    converterClass="org.springframework.boot.logging.logback.WhitespaceThrowableProxyConverter"/>

    <!-- ── Local profile: human-readable colored console ──────────────────── -->
    <springProfile name="local">
        <appender name="CONSOLE" class="ch.qos.logback.core.ConsoleAppender">
            <encoder>
                <pattern>%clr(%d{HH:mm:ss.SSS}){faint} %clr(%5p) %clr(---){faint} %clr([%15.15t]){faint} %clr(%-40.40logger{39}){cyan} %clr(:){faint} %m%n%wEx</pattern>
                <charset>UTF-8</charset>
            </encoder>
        </appender>

        <root level="INFO">
            <appender-ref ref="CONSOLE"/>
        </root>
    </springProfile>

    <!-- ── All other profiles (prod / default): JSON to stdout ────────────── -->
    <springProfile name="!local">
        <appender name="JSON_CONSOLE" class="ch.qos.logback.core.ConsoleAppender">
            <encoder class="net.logstash.logback.encoder.LogstashEncoder">
                <!-- Remove redundant fields already present in the JSON structure -->
                <excludeMdcKeyName>HOSTNAME</excludeMdcKeyName>
                <!-- Shorten logger name to keep lines compact -->
                <shortenedLoggerNameLength>36</shortenedLoggerNameLength>
                <!-- Include stack traces as a JSON array field -->
                <throwableConverter class="net.logstash.logback.stacktrace.ShortenedThrowableConverter">
                    <maxDepthPerCause>10</maxDepthPerCause>
                    <rootCauseFirst>true</rootCauseFirst>
                </throwableConverter>
            </encoder>
        </appender>

        <root level="INFO">
            <appender-ref ref="JSON_CONSOLE"/>
        </root>
    </springProfile>

</configuration>
